{
    "total_time_ns": 225155227,
    "total_allocated_bytes": 200401816,
    "time_ns": 0,
    "n_calls": 0,
    "allocated_bytes": 0,
    "inner_timers": {
        "mult f": {
            "total_time_ns": 0,
            "total_allocated_bytes": 0,
            "time_ns": 100980,
            "n_calls": 1,
            "allocated_bytes": 2720,
            "inner_timers": {}
        },
        "eval Ut": {
            "total_time_ns": 0,
            "total_allocated_bytes": 0,
            "time_ns": 8461443,
            "n_calls": 1,
            "allocated_bytes": 272,
            "inner_timers": {}
        },
        "A": {
            "total_time_ns": 0,
            "total_allocated_bytes": 0,
            "time_ns": 34056570,
            "n_calls": 1,
            "allocated_bytes": 83157536,
            "inner_timers": {}
        },
        "init cg vars": {
            "total_time_ns": 0,
            "total_allocated_bytes": 0,
            "time_ns": 14306,
            "n_calls": 1,
            "allocated_bytes": 6291896,
            "inner_timers": {}
        },
        "L": {
            "total_time_ns": 0,
            "total_allocated_bytes": 0,
            "time_ns": 122453570,
            "n_calls": 1,
            "allocated_bytes": 106746632,
            "inner_timers": {}
        },
        "solve CG": {
            "total_time_ns": 0,
            "total_allocated_bytes": 0,
            "time_ns": 7513630,
            "n_calls": 1,
            "allocated_bytes": 1760,
            "inner_timers": {}
        },
        "init Ut": {
            "total_time_ns": 0,
            "total_allocated_bytes": 0,
            "time_ns": 42890112,
            "n_calls": 1,
            "allocated_bytes": 2101984,
            "inner_timers": {}
        },
        "add to Ut": {
            "total_time_ns": 0,
            "total_allocated_bytes": 0,
            "time_ns": 152116,
            "n_calls": 1,
            "allocated_bytes": 224,
            "inner_timers": {}
        },
        "eval f": {
            "total_time_ns": 0,
            "total_allocated_bytes": 0,
            "time_ns": 9243104,
            "n_calls": 1,
            "allocated_bytes": 272,
            "inner_timers": {}
        },
        "post cg": {
            "total_time_ns": 0,
            "total_allocated_bytes": 0,
            "time_ns": 249750,
            "n_calls": 1,
            "allocated_bytes": 208,
            "inner_timers": {}
        },
        "create f_fun": {
            "total_time_ns": 0,
            "total_allocated_bytes": 0,
            "time_ns": 3887,
            "n_calls": 1,
            "allocated_bytes": 496,
            "inner_timers": {}
        },
        "init buffer": {
            "total_time_ns": 0,
            "total_allocated_bytes": 0,
            "time_ns": 12363,
            "n_calls": 1,
            "allocated_bytes": 2097416,
            "inner_timers": {}
        },
        "create u_fun": {
            "total_time_ns": 0,
            "total_allocated_bytes": 0,
            "time_ns": 3396,
            "n_calls": 1,
            "allocated_bytes": 400,
            "inner_timers": {}
        }
    }
}
